skycatalogs/__init__.py
skycatalogs/_version.py
skycatalogs/skyCatalogs.py
skycatalogs/data/ci_sample/README
skycatalogs/data/ci_sample/cosmodc2_bulge.yaml
skycatalogs/data/ci_sample/cosmodc2_disk.yaml
skycatalogs/data/ci_sample/cosmodc2_galaxy.yaml
skycatalogs/data/ci_sample/cosmodc2_knots.yaml
skycatalogs/data/ci_sample/dc2_star.yaml
skycatalogs/data/ci_sample/gaia_skyCatalog.yaml
skycatalogs/data/ci_sample/galaxy_1.3.0.yaml
skycatalogs/data/ci_sample/galaxy_9556.parquet
skycatalogs/data/ci_sample/galaxy_9557.parquet
skycatalogs/data/ci_sample/galaxy_9683.parquet
skycatalogs/data/ci_sample/galaxy_9684.parquet
skycatalogs/data/ci_sample/galaxy_9812.parquet
skycatalogs/data/ci_sample/galaxy_9813.parquet
skycatalogs/data/ci_sample/galaxy_9940.parquet
skycatalogs/data/ci_sample/galaxy_flux_9556.parquet
skycatalogs/data/ci_sample/galaxy_flux_9683.parquet
skycatalogs/data/ci_sample/galaxy_flux_9684.parquet
skycatalogs/data/ci_sample/galaxy_flux_9813.parquet
skycatalogs/data/ci_sample/galaxy_flux_9940.parquet
skycatalogs/data/ci_sample/pointsource_9556.parquet
skycatalogs/data/ci_sample/pointsource_9683.parquet
skycatalogs/data/ci_sample/pointsource_9684.parquet
skycatalogs/data/ci_sample/pointsource_9812.parquet
skycatalogs/data/ci_sample/pointsource_9813.parquet
skycatalogs/data/ci_sample/pointsource_9940.parquet
skycatalogs/data/ci_sample/pointsource_flux_9556.parquet
skycatalogs/data/ci_sample/pointsource_flux_9683.parquet
skycatalogs/data/ci_sample/pointsource_flux_9684.parquet
skycatalogs/data/ci_sample/pointsource_flux_9813.parquet
skycatalogs/data/ci_sample/pointsource_flux_9940.parquet
skycatalogs/data/ci_sample/skyCatalog.yaml
skycatalogs/data/ci_sample/skyCatalog_top.yaml
skycatalogs/data/ci_sample/star_1.3.0.yaml
skycatalogs/data/ci_sample/top_1.3.0.yaml
skycatalogs/data/ci_sample/trilegal.yaml
skycatalogs/data/ci_sample/trilegal_9556.parquet
skycatalogs/data/ci_sample/trilegal_9683.parquet
skycatalogs/data/ci_sample/trilegal_9684.parquet
skycatalogs-2.3.0.dist-info/licenses/LICENSE
skycatalogs-2.3.0.dist-info/METADATA
skycatalogs-2.3.0.dist-info/WHEEL
skycatalogs-2.3.0.dist-info/top_level.txt
skycatalogs-2.3.0.dist-info/RECORD
