Metadata-Version: 2.4
Name: skyCatalogs
Version: 2.3.0
Summary: Writes, reads catalogs input to LSST DESC simulations
Author-email: Joanne Bogart <jrb@slac.stanford.edu>
License: Copyright (c) 2018, the skyCatalogs contributors on GitHub, https://github.com/LSSTDESC/skyCatalogs/graphs/contributors.
Keywords: desc,python,catalog,simulation
Classifier: Programming Language :: Python :: 3
Requires-Python: >=3.9
License-File: LICENSE
Requires-Dist: astropy
Requires-Dist: dust_extinction
Requires-Dist: dustmaps
Requires-Dist: esutil
Requires-Dist: galsim
Requires-Dist: h5py
Requires-Dist: healpy
Requires-Dist: lsst-sphgeom
Requires-Dist: lsstdesc_diffsky
Requires-Dist: numpy
Requires-Dist: pandas
Requires-Dist: pyarrow
Requires-Dist: pyerfa
Requires-Dist: pyyaml
Dynamic: license-file
